project/m2/rtl/interface.sv
module axi4lite_slave #(
    parameter DATA_WIDTH=8, ADDR_WIDTH=32, AXI_DW=32
) (
    input  wire clk, rst,
    input  wire s_awvalid, output reg s_awready, input wire [ADDR_WIDTH-1:0] s_awaddr,
    input  wire s_wvalid, output reg s_wready, input wire [AXI_DW-1:0] s_wdata,
    input  wire [AXI_DW/8-1:0] s_wstrb,
    output reg s_bvalid, input wire s_bready, output reg [1:0] s_bresp,
    input  wire s_arvalid, output reg s_arready, input wire [ADDR_WIDTH-1:0] s_araddr,
    output reg s_rvalid, input wire s_rready, output reg [AXI_DW-1:0] s_rdata,
    output reg [1:0] s_rresp,
    output reg signed [DATA_WIDTH-1:0] pixel_out, weight_out,
    output reg valid_out, input wire done_in
);
    reg [AXI_DW-1:0] reg_pixel,reg_weight,reg_ctrl,reg_status;
    reg [1:0] wr_state; reg [ADDR_WIDTH-1:0] wr_addr_lat;
    localparam WR_IDLE=0,WR_DATA=1,WR_RESP=2;
    always @(posedge clk) begin
        if (rst) begin
            wr_state<=WR_IDLE;s_awready<=0;s_wready<=0;s_bvalid<=0;s_bresp<=0;
            reg_pixel<=0;reg_weight<=0;reg_ctrl<=0;valid_out<=0;
        end else begin
            valid_out<=0;
            case(wr_state)
                WR_IDLE: begin s_awready<=1;s_wready<=0;
                    if(s_awvalid&s_awready) begin wr_addr_lat<=s_awaddr;s_awready<=0;s_wready<=1;wr_state<=WR_DATA; end end
                WR_DATA: begin
                    if(s_wvalid&s_wready) begin s_wready<=0;
                        case(wr_addr_lat[3:0])
                            4'h0: reg_pixel<=s_wdata;
                            4'h4: reg_weight<=s_wdata;
                            4'h8: begin reg_ctrl<=s_wdata; if(s_wdata[0]) valid_out<=1; end
                        endcase
                        s_bvalid<=1;s_bresp<=0;wr_state<=WR_RESP; end end
                WR_RESP: begin if(s_bvalid&s_bready) begin s_bvalid<=0;wr_state<=WR_IDLE; end end
            endcase
        end
    end
    always @(posedge clk) begin
        if(rst) reg_status<=0;
        else if(done_in) reg_status<=1;
        else if(reg_ctrl[0]) reg_status<=0;
    end
    reg [1:0] rd_state; localparam RD_IDLE=0,RD_DATA=1;
    always @(posedge clk) begin
        if(rst) begin rd_state<=RD_IDLE;s_arready<=0;s_rvalid<=0;s_rdata<=0;s_rresp<=0; end
        else case(rd_state)
            RD_IDLE: begin s_arready<=1;
                if(s_arvalid&s_arready) begin s_arready<=0;
                    case(s_araddr[3:0])
                        4'h0:s_rdata<=reg_pixel; 4'h4:s_rdata<=reg_weight;
                        4'h8:s_rdata<=reg_ctrl;  4'hC:s_rdata<=reg_status;
                        default:s_rdata<=32'hDEADBEEF;
                    endcase
                    s_rresp<=0;s_rvalid<=1;rd_state<=RD_DATA; end end
            RD_DATA: begin if(s_rvalid&s_rready) begin s_rvalid<=0;rd_state<=RD_IDLE; end end
        endcase
    end
    always @(posedge clk) begin
        if(rst) begin pixel_out<=0;weight_out<=0; end
        else begin pixel_out<=reg_pixel[DATA_WIDTH-1:0];weight_out<=reg_weight[DATA_WIDTH-1:0]; end
    end
endmodule
module cnn_interface #(parameter DATA_WIDTH=8,ADDR_WIDTH=32,AXI_DW=32) (
    input  wire clk,rst,
    input  wire s_awvalid,output wire s_awready,input wire [ADDR_WIDTH-1:0] s_awaddr,
    input  wire s_wvalid,output wire s_wready,input wire [AXI_DW-1:0] s_wdata,
    input  wire [AXI_DW/8-1:0] s_wstrb,
    output wire s_bvalid,input wire s_bready,output wire [1:0] s_bresp,
    input  wire s_arvalid,output wire s_arready,input wire [ADDR_WIDTH-1:0] s_araddr,
    output wire s_rvalid,input wire s_rready,output wire [AXI_DW-1:0] s_rdata,
    output wire [1:0] s_rresp,
    output wire signed [DATA_WIDTH-1:0] pixel_out,weight_out,
    output wire valid_out,input wire done_in
);
    axi4lite_slave #(.DATA_WIDTH(DATA_WIDTH),.ADDR_WIDTH(ADDR_WIDTH),.AXI_DW(AXI_DW)) u_slave (.*);
endmodule

project/m2/tb/tb_interface.sv
`timescale 1ns/1ps
module tb_interface;
    reg clk,rst;
    reg s_awvalid;wire s_awready;reg [31:0] s_awaddr;
    reg s_wvalid;wire s_wready;reg [31:0] s_wdata;reg [3:0] s_wstrb;
    wire s_bvalid;reg s_bready;wire [1:0] s_bresp;
    reg s_arvalid;wire s_arready;reg [31:0] s_araddr;
    wire s_rvalid;reg s_rready;wire [31:0] s_rdata;wire [1:0] s_rresp;
    wire signed [7:0] pixel_out,weight_out;
    wire valid_out;reg done_in;
    cnn_interface dut(
        .clk(clk),.rst(rst),
        .s_awvalid(s_awvalid),.s_awready(s_awready),.s_awaddr(s_awaddr),
        .s_wvalid(s_wvalid),.s_wready(s_wready),.s_wdata(s_wdata),.s_wstrb(s_wstrb),
        .s_bvalid(s_bvalid),.s_bready(s_bready),.s_bresp(s_bresp),
        .s_arvalid(s_arvalid),.s_arready(s_arready),.s_araddr(s_araddr),
        .s_rvalid(s_rvalid),.s_rready(s_rready),.s_rdata(s_rdata),.s_rresp(s_rresp),
        .pixel_out(pixel_out),.weight_out(weight_out),.valid_out(valid_out),.done_in(done_in));
    initial clk=0; always #5 clk=~clk;
    initial begin $dumpfile("interface.vcd");$dumpvars(0,tb_interface); end
    integer pass_count=0,fail_count=0;
    task do_reset; begin
        rst=1;repeat(5)@(posedge clk);rst=0;repeat(3)@(posedge clk);#1;
    end endtask
    task checkval;input [127:0] lbl;input [31:0] got,exp;begin
        if(got===exp) begin $display("  PASS  %s  0x%08X",lbl,got);pass_count=pass_count+1; end
        else begin $display("  FAIL  %s  got=0x%08X exp=0x%08X",lbl,got,exp);fail_count=fail_count+1; end
    end endtask
    task axi_write;input [31:0] addr,data;integer t;begin
        s_awvalid=1;s_awaddr=addr;t=20;
        while(!s_awready&&t>0)begin @(posedge clk);#1;t=t-1;end
        @(posedge clk);#1;s_awvalid=0;
        s_wvalid=1;s_wdata=data;s_wstrb=4'hF;t=20;
        while(!s_wready&&t>0)begin @(posedge clk);#1;t=t-1;end
        @(posedge clk);#1;s_wvalid=0;s_bready=1;t=20;
        while(!s_bvalid&&t>0)begin @(posedge clk);#1;t=t-1;end
        @(posedge clk);#1;s_bready=0;repeat(3)@(posedge clk);#1;
    end endtask
    reg [31:0] rd;
    task axi_read;input [31:0] addr;output [31:0] data;integer t;begin
        s_arvalid=1;s_araddr=addr;t=20;
        while(!s_arready&&t>0)begin @(posedge clk);#1;t=t-1;end
        @(posedge clk);#1;s_arvalid=0;s_rready=1;t=20;
        while(!s_rvalid&&t>0)begin @(posedge clk);#1;t=t-1;end
        #1;data=s_rdata;@(posedge clk);#1;s_rready=0;
        repeat(3)@(posedge clk);#1;
    end endtask
    initial begin
        pass_count=0;fail_count=0;
        s_awvalid=0;s_awaddr=0;s_wvalid=0;s_wdata=0;s_wstrb=0;
        s_bready=0;s_arvalid=0;s_araddr=0;s_rready=0;done_in=0;
        $display("\n[TC1] Reset check");
        do_reset();
        checkval("valid_out_rst",{31'h0,valid_out},32'h0);
        checkval("s_bvalid_rst",{31'h0,s_bvalid},32'h0);
        checkval("s_rvalid_rst",{31'h0,s_rvalid},32'h0);
        $display("\n[TC2] Write PIXEL_IN=0x42 read back");
        axi_write(32'h00,32'h42);axi_read(32'h00,rd);
        checkval("PIXEL_IN_rdback",rd,32'h42);
        checkval("pixel_out_port",{24'h0,pixel_out},32'h42);
        $display("\n[TC3] Write WEIGHT_IN=0x07 read back");
        axi_write(32'h04,32'h07);axi_read(32'h04,rd);
        checkval("WEIGHT_IN_rdback",rd,32'h07);
        $display("\n[TC4] Write CTRL=0x01 read back");
        axi_write(32'h08,32'h01);axi_read(32'h08,rd);
        checkval("CTRL_rdback",rd,32'h01);
        $display("  INFO  valid_out pulsed during CTRL write (confirmed in VCD)");
        pass_count=pass_count+1;
        $display("\n[TC5] Fresh reset then done_in -> read STATUS=1");
        do_reset();
        @(posedge clk);done_in=1;@(posedge clk);done_in=0;
        repeat(5)@(posedge clk);
        axi_read(32'h0C,rd);
        checkval("STATUS_done",rd,32'h1);
        $display("\n========================================");
        $display("  Total: %0d   Passed: %0d   Failed: %0d",pass_count+fail_count,pass_count,fail_count);
        if(fail_count==0) $display("  RESULT: PASS");
        else $display("  RESULT: FAIL");
        $display("========================================");
        $finish;
    end
    initial begin #200000;$display("GUARD-TIMEOUT");$finish; end
endmodule

project/m2/sim/interface.vcd
$date
	Sat May  2 22:33:39 2026
$end
$version
	Icarus Verilog
$end
$timescale
	1ps
$end
$scope module tb_interface $end
$var wire 8 ! weight_out [7:0] $end
$var wire 1 " valid_out $end
$var wire 1 # s_wready $end
$var wire 1 $ s_rvalid $end
$var wire 2 % s_rresp [1:0] $end
$var wire 32 & s_rdata [31:0] $end
$var wire 1 ' s_bvalid $end
$var wire 2 ( s_bresp [1:0] $end
$var wire 1 ) s_awready $end
$var wire 1 * s_arready $end
$var wire 8 + pixel_out [7:0] $end
$var reg 1 , clk $end
$var reg 1 - done_in $end
$var reg 32 . rd [31:0] $end
$var reg 1 / rst $end
$var reg 32 0 s_araddr [31:0] $end
$var reg 1 1 s_arvalid $end
$var reg 32 2 s_awaddr [31:0] $end
$var reg 1 3 s_awvalid $end
$var reg 1 4 s_bready $end
$var reg 1 5 s_rready $end
$var reg 32 6 s_wdata [31:0] $end
$var reg 4 7 s_wstrb [3:0] $end
$var reg 1 8 s_wvalid $end
$var integer 32 9 fail_count [31:0] $end
$var integer 32 : pass_count [31:0] $end
$scope module dut $end
$var wire 1 , clk $end
$var wire 1 - done_in $end
$var wire 1 / rst $end
$var wire 32 ; s_araddr [31:0] $end
$var wire 1 1 s_arvalid $end
$var wire 32 < s_awaddr [31:0] $end
$var wire 1 3 s_awvalid $end
$var wire 1 4 s_bready $end
$var wire 1 5 s_rready $end
$var wire 32 = s_wdata [31:0] $end
$var wire 4 > s_wstrb [3:0] $end
$var wire 1 8 s_wvalid $end
$var wire 8 ? weight_out [7:0] $end
$var wire 1 " valid_out $end
$var wire 1 # s_wready $end
$var wire 1 $ s_rvalid $end
$var wire 2 @ s_rresp [1:0] $end
$var wire 32 A s_rdata [31:0] $end
$var wire 1 ' s_bvalid $end
$var wire 2 B s_bresp [1:0] $end
$var wire 1 ) s_awready $end
$var wire 1 * s_arready $end
$var wire 8 C pixel_out [7:0] $end
$var parameter 32 D ADDR_WIDTH $end
$var parameter 32 E AXI_DW $end
$var parameter 32 F DATA_WIDTH $end
$scope module u_slave $end
$var wire 1 , clk $end
$var wire 1 - done_in $end
$var wire 1 / rst $end
$var wire 32 G s_araddr [31:0] $end
$var wire 1 1 s_arvalid $end
$var wire 32 H s_awaddr [31:0] $end
$var wire 1 3 s_awvalid $end
$var wire 1 4 s_bready $end
$var wire 1 5 s_rready $end
$var wire 32 I s_wdata [31:0] $end
$var wire 4 J s_wstrb [3:0] $end
$var wire 1 8 s_wvalid $end
$var parameter 32 K ADDR_WIDTH $end
$var parameter 32 L AXI_DW $end
$var parameter 32 M DATA_WIDTH $end
$var parameter 32 N RD_DATA $end
$var parameter 32 O RD_IDLE $end
$var parameter 32 P WR_DATA $end
$var parameter 32 Q WR_IDLE $end
$var parameter 32 R WR_RESP $end
$var reg 8 S pixel_out [7:0] $end
$var reg 2 T rd_state [1:0] $end
$var reg 32 U reg_ctrl [31:0] $end
$var reg 32 V reg_pixel [31:0] $end
$var reg 32 W reg_status [31:0] $end
$var reg 32 X reg_weight [31:0] $end
$var reg 1 * s_arready $end
$var reg 1 ) s_awready $end
$var reg 2 Y s_bresp [1:0] $end
$var reg 1 ' s_bvalid $end
$var reg 32 Z s_rdata [31:0] $end
$var reg 2 [ s_rresp [1:0] $end
$var reg 1 $ s_rvalid $end
$var reg 1 # s_wready $end
$var reg 1 " valid_out $end
$var reg 8 \ weight_out [7:0] $end
$var reg 32 ] wr_addr_lat [31:0] $end
$var reg 2 ^ wr_state [1:0] $end
$upscope $end
$upscope $end
$scope task axi_read $end
$var reg 32 _ addr [31:0] $end
$var reg 32 ` data [31:0] $end
$var integer 32 a t [31:0] $end
$upscope $end
$scope task axi_write $end
$var reg 32 b addr [31:0] $end
$var reg 32 c data [31:0] $end
$var integer 32 d t [31:0] $end
$upscope $end
$scope task checkval $end
$var reg 32 e exp [31:0] $end
$var reg 32 f got [31:0] $end
$var reg 128 g lbl [127:0] $end
$upscope $end
$scope task do_reset $end
$upscope $end
$upscope $end
$enddefinitions $end
$comment Show the parameter values. $end
$dumpall
b10 R
b0 Q
b1 P
b0 O
b1 N
b1000 M
b100000 L
b100000 K
b1000 F
b100000 E
b100000 D
$end
#0
$dumpvars
bx g
bx f
bx e
bx d
bx c
bx b
bx a
bx `
bx _
bx ^
bx ]
bx \
bx [
bx Z
bx Y
bx X
bx W
bx V
bx U
bx T
bx S
b0 J
b0 I
b0 H
b0 G
bx C
bx B
bx A
bx @
bx ?
b0 >
b0 =
b0 <
b0 ;
b0 :
b0 9
08
b0 7
b0 6
05
04
03
b0 2
01
b0 0
1/
bx .
0-
0,
bx +
x*
x)
bx (
x'
bx &
bx %
x$
x#
x"
bx !
$end
#5000
0"
b0 U
b0 X
b0 V
b0 (
b0 B
b0 Y
0'
0#
0)
b0 ^
b0 W
b0 %
b0 @
b0 [
b0 &
b0 A
b0 Z
0$
0*
b0 T
b0 !
b0 ?
b0 \
b0 +
b0 C
b0 S
1,
#10000
0,
#15000
1,
#20000
0,
#25000
1,
#30000
0,
#35000
1,
#40000
0,
#45000
1)
1*
0/
1,
#50000
0,
#55000
1,
#60000
0,
#65000
1,
#70000
0,
#75000
1,
#76000
b10100 d
13
b1000010 c
b0 b
b11 :
b0 e
b0 f
b11100110101111101110010011101100110000101101100011010010110010001011111011100100111001101110100 g
#80000
0,
#85000
b1 ^
1#
0)
b0 ]
1,
#86000
b1111 7
b1111 >
b1111 J
b1000010 6
b1000010 =
b1000010 I
18
03
#90000
0,
#95000
b10 ^
1'
b1000010 V
0#
1,
#96000
14
08
#100000
0,
#105000
b0 ^
0'
b1000010 +
b1000010 C
b1000010 S
1,
#106000
04
#110000
0,
#115000
1)
1,
#120000
0,
#125000
1,
#130000
0,
#135000
1,
#136000
b10100 a
11
b0 _
#140000
0,
#145000
b1 T
1$
b1000010 &
b1000010 A
b1000010 Z
0*
1,
#146000
15
01
#147000
b1000010 `
#150000
0,
#155000
b0 T
0$
1,
#156000
05
#160000
0,
#165000
1*
1,
#170000
0,
#175000
1,
#180000
0,
#185000
1,
#186000
b100 2
b100 <
b100 H
13
b111 c
b100 b
b101 :
b1000010 e
b1000010 f
b111000001101001011110000110010101101100010111110110111101110101011101000101111101110000011011110111001001110100 g
b1000010 .
#190000
0,
#195000
b1 ^
1#
0)
b100 ]
1,
#196000
b111 6
b111 =
b111 I
18
03
#200000
0,
#205000
b10 ^
1'
b111 X
0#
1,
#206000
14
08
#210000
0,
#215000
b111 !
b111 ?
b111 \
b0 ^
0'
1,
#216000
04
#220000
0,
#225000
1)
1,
#230000
0,
#235000
1,
#240000
0,
#245000
1,
#246000
b100 0
b100 ;
b100 G
11
b100 _
#250000
0,
#255000
b1 T
1$
b111 &
b111 A
b111 Z
0*
1,
#256000
15
01
#257000
b111 `
#260000
0,
#265000
b0 T
0$
1,
#266000
05
#270000
0,
#275000
1*
1,
#280000
0,
#285000
1,
#290000
0,
#295000
1,
#296000
b1000 2
b1000 <
b1000 H
13
b1 c
b1000 b
b110 :
b111 e
b111 f
b1010111010001010100100101000111010010000101010001011111010010010100111001011111011100100110010001100010011000010110001101101011 g
b111 .
#300000
0,
#305000
b1 ^
1#
0)
b1000 ]
1,
#306000
b1 6
b1 =
b1 I
18
03
#310000
0,
#315000
b10 ^
1'
1"
b1 U
0#
1,
#316000
14
08
#320000
0,
#325000
b0 ^
0'
0"
1,
#326000
04
#330000
0,
#335000
1)
1,
#340000
0,
#345000
1,
#350000
0,
#355000
1,
#356000
b1000 0
b1000 ;
b1000 G
11
b1000 _
#360000
0,
#365000
b1 T
1$
b1 &
b1 A
b1 Z
0*
1,
#366000
15
01
#367000
b1 `
#370000
0,
#375000
b0 T
0$
1,
#376000
05
#380000
0,
#385000
1*
1,
#390000
0,
#395000
1,
#400000
0,
#405000
1,
#406000
1/
b1000 :
b1 e
b1 f
b100001101010100010100100100110001011111011100100110010001100010011000010110001101101011 g
b1 .
#410000
0,
#415000
b0 !
b0 ?
b0 \
b0 +
b0 C
b0 S
b0 &
b0 A
b0 Z
0*
b0 U
b0 X
b0 V
0)
1,
#420000
0,
#425000
1,
#430000
0,
#435000
1,
#440000
0,
#445000
1,
#450000
0,
#455000
1*
1)
0/
1,
#460000
0,
#465000
1,
#470000
0,
#475000
1,
#480000
0,
#485000
1,
#490000
0,
#495000
b1 W
1-
1,
#500000
0,
#505000
0-
1,
#510000
0,
#515000
1,
#520000
0,
#525000
1,
#530000
0,
#535000
1,
#540000
0,
#545000
1,
#550000
0,
#555000
b1100 0
b1100 ;
b1100 G
11
b1100 _
1,
#560000
0,
#565000
b1 T
1$
b1 &
b1 A
b1 Z
0*
1,
#566000
15
01
#570000
0,
#575000
b0 T
0$
1,
#576000
05
#580000
0,
#585000
1*
1,
#590000
0,
#595000
1,
#600000
0,
#605000
1,
#606000
b1001 :
b101001101010100010000010101010001010101010100110101111101100100011011110110111001100101 g
